pymodaq_plugins_datamixer/__init__.py
pymodaq_plugins_datamixer/utils.py
pymodaq_plugins_datamixer/app/__init__.py
pymodaq_plugins_datamixer/daq_move_plugins/__init__.py
pymodaq_plugins_datamixer/daq_viewer_plugins/__init__.py
pymodaq_plugins_datamixer/daq_viewer_plugins/plugins_0D/__init__.py
pymodaq_plugins_datamixer/daq_viewer_plugins/plugins_0D/daq_0Dviewer_DataMixer.py
pymodaq_plugins_datamixer/daq_viewer_plugins/plugins_1D/__init__.py
pymodaq_plugins_datamixer/daq_viewer_plugins/plugins_2D/__init__.py
pymodaq_plugins_datamixer/daq_viewer_plugins/plugins_ND/__init__.py
pymodaq_plugins_datamixer/exporters/__init__.py
pymodaq_plugins_datamixer/extensions/__init__.py
pymodaq_plugins_datamixer/extensions/data_mixer.py
pymodaq_plugins_datamixer/extensions/utils/__init__.py
pymodaq_plugins_datamixer/extensions/utils/model.py
pymodaq_plugins_datamixer/extensions/utils/parser.py
pymodaq_plugins_datamixer/hardware/__init__.py
pymodaq_plugins_datamixer/models/__init__.py
pymodaq_plugins_datamixer/models/equation_model.py
pymodaq_plugins_datamixer/models/fit_model.py
pymodaq_plugins_datamixer/models/harmonics_model.py
pymodaq_plugins_datamixer/resources/__init__.py
pymodaq_plugins_datamixer/resources/config_template.toml
pymodaq_plugins_datamixer/scanners/__init__.py
pymodaq_plugins_datamixer-0.0.6.dist-info/METADATA
pymodaq_plugins_datamixer-0.0.6.dist-info/WHEEL
pymodaq_plugins_datamixer-0.0.6.dist-info/entry_points.txt
pymodaq_plugins_datamixer-0.0.6.dist-info/licenses/LICENSE
pymodaq_plugins_datamixer-0.0.6.dist-info/RECORD
